pulse_throw.py
pulse_throw-0.1.0.dist-info/LICENSE
pulse_throw-0.1.0.dist-info/WHEEL
pulse_throw-0.1.0.dist-info/METADATA
pulse_throw-0.1.0.dist-info/RECORD
