Metadata-Version: 2.1
Name: pulse-throw
Version: 0.1.0
Summary: Tools for acquiring and analyzing Pulse API data.
Home-page: https://github.com/hedgertronic/pulse-throw
License: MIT
Author: Josh Hejka
Author-email: josh@joshhejka.com
Requires-Python: >=3.10,<4.0
Classifier: License :: OSI Approved :: MIT License
Classifier: Programming Language :: Python :: 3
Classifier: Programming Language :: Python :: 3.10
Requires-Dist: Authlib (>=1.0.1,<2.0.0)
Requires-Dist: requests (>=2.28.1,<3.0.0)
Project-URL: Repository, https://github.com/hedgertronic/pulse-throw
